datavns/__init__.py
datavns/bond_data.py
datavns/fund_data.py
datavns/headers.py
datavns/indicator.py
datavns/lib.py
datavns/macro_data.py
datavns/stock_data.py
datavns-0.1.37.dist-info/licenses/LICENSE
datavns-0.1.37.dist-info/METADATA
datavns-0.1.37.dist-info/WHEEL
datavns-0.1.37.dist-info/top_level.txt
datavns-0.1.37.dist-info/RECORD
