Metadata-Version: 2.4
Name: datavns
Version: 0.1.37
Summary: A package to collect and backtest the trading strategy on Vietnam stocks market
Author-email: the-a1pha <buitruonganbta@gmail.com>
Project-URL: Homepage, https://github.com/the-a1pha/datavns
Project-URL: Issues, https://github.com/the-a1pha/datavns/issues
Classifier: Programming Language :: Python :: 3
Classifier: License :: OSI Approved :: MIT License
Classifier: Operating System :: OS Independent
Requires-Python: >=3.8
License-File: LICENSE
Dynamic: license-file
